sdr_classifier/__init__.py
sdr_classifier/prep_utils.py
sdr_classifier/sdr_api.py
sdr_classifier/sdr_classifier.py
sdr_classifier/sdr_data_preparer.py
sdr_classifier/vectorizers.py
sdr_classifier/data/Corrosion_Limit.csv
sdr_classifier/data/Degraded_Controllability.csv
sdr_classifier/data/Depressurization.csv
sdr_classifier/data/SDR_Example.csv
sdr_classifier/model/sdr-corrosion-limit.config
sdr_classifier/model/sdr-corrosion-limit.model
sdr_classifier/model/sdr-degraded-controllability.config
sdr_classifier/model/sdr-degraded-controllability.model
sdr_classifier/model/sdr-depressurization.config
sdr_classifier/model/sdr-depressurization.model
sdr_classifier-0.0.2.dist-info/LICENSE
sdr_classifier-0.0.2.dist-info/METADATA
sdr_classifier-0.0.2.dist-info/WHEEL
sdr_classifier-0.0.2.dist-info/top_level.txt
sdr_classifier-0.0.2.dist-info/RECORD
