Metadata-Version: 2.1
Name: sdr-classifier
Version: 0.0.2
Summary: Package to create SDR Classifier
Home-page: 
Author: Hai Nguyen
Author-email: hai.c.nguyen@boeing.com
Classifier: Programming Language :: Python :: 3
Classifier: License :: OSI Approved :: MIT License
Classifier: Operating System :: OS Independent
Requires-Python: >=3.6
License-File: LICENSE
Requires-Dist: pandas >=1.1.5
Requires-Dist: scikit-learn >=0.24.1
